make_py/__init__.py
make_py/__main__.py
make_py/executor.py
make_py/filesystem.py
make_py/matcher.py
make_py/persistence.py
make_py/task.py
make_py/task_gen.py
make_py/util.py
make_py-0.1.1.dist-info/LICENSE
make_py-0.1.1.dist-info/METADATA
make_py-0.1.1.dist-info/WHEEL
make_py-0.1.1.dist-info/entry_points.txt
make_py-0.1.1.dist-info/top_level.txt
make_py-0.1.1.dist-info/RECORD
