Metadata-Version: 2.1
Name: make-py
Version: 0.1.1
Summary: A make equivalent in Python
Home-page: https://github.com/cww0614/make.py
Author: Yifei Wang
Author-email: yifei529@gmail.com
License: UNKNOWN
Platform: UNKNOWN
Classifier: Programming Language :: Python :: 3
Classifier: License :: OSI Approved :: MIT License
Classifier: Operating System :: OS Independent
Requires-Python: >=3.6
